{
  "question_replacement": false,
  "response_replacement": false,
  "gen_responsetype": "text_data",
  "question_count": 10,
  "banner_color": "#000066",
  "gen_answerSet": [],
  "gen_responseSet": [],
  "gen_answertype": "text_data",
  "gen_stimulusSet": [],
  "gen_stimulustype": "text_data",
  "question_sequence": "RANDOM",
  "problem_type": "MIS_NUM",
  "dataSource": [
    {
      "question_say": true,
      "question_show": true,
      "answer_type": "text_data",
      "answer": 547,
      "question_type": "multiple-choice",
      "stimulus_type": "text_data",
      "responsetype_set": [
        "text_data",
        "text_data",
        "text_data"
      ],
      "stimulus": "546, __, 548, 549",
      "response_set": [
        776,
        587,
        547
      ],
      "gen_question": false
    },
    {
      "question_say": true,
      "question_show": true,
      "answer_type": "text_data",
      "answer": 285,
      "question_type": "multiple-choice",
      "stimulus_type": "text_data",
      "responsetype_set": [
        "text_data",
        "text_data",
        "text_data"
      ],
      "stimulus": "284, __, 286, 287",
      "response_set": [
        608,
        285,
        879
      ],
      "gen_question": false
    },
    {
      "question_say": true,
      "question_show": true,
      "answer_type": "text_data",
      "answer": 875,
      "question_type": "multiple-choice",
      "stimulus_type": "text_data",
      "responsetype_set": [
        "text_data",
        "text_data",
        "text_data"
      ],
      "stimulus": "874, __, 876, 877",
      "response_set": [
        689,
        875,
        804
      ],
      "gen_question": false
    },
    {
      "question_say": true,
      "question_show": true,
      "answer_type": "text_data",
      "answer": 313,
      "question_type": "multiple-choice",
      "stimulus_type": "text_data",
      "responsetype_set": [
        "text_data",
        "text_data",
        "text_data"
      ],
      "stimulus": "312, __, 314, 315",
      "response_set": [
        313,
        730,
        532
      ],
      "gen_question": false
    },
    {
      "question_say": true,
      "question_show": true,
      "answer_type": "text_data",
      "answer": 871,
      "question_type": "multiple-choice",
      "stimulus_type": "text_data",
      "responsetype_set": [
        "text_data",
        "text_data",
        "text_data"
      ],
      "stimulus": "870, __, 872, 873",
      "response_set": [
        616,
        643,
        871
      ],
      "gen_question": false
    },
    {
      "question_say": true,
      "question_show": true,
      "answer_type": "text_data",
      "answer": 243,
      "question_type": "multiple-choice",
      "stimulus_type": "text_data",
      "responsetype_set": [
        "text_data",
        "text_data",
        "text_data"
      ],
      "stimulus": "242, __, 244, 245",
      "response_set": [
        762,
        378,
        243
      ],
      "gen_question": false
    },
    {
      "question_say": true,
      "question_show": true,
      "answer_type": "text_data",
      "answer": 561,
      "question_type": "multiple-choice",
      "stimulus_type": "text_data",
      "responsetype_set": [
        "text_data",
        "text_data",
        "text_data"
      ],
      "stimulus": "560, __, 562, 563",
      "response_set": [
        561,
        500,
        633
      ],
      "gen_question": false
    },
    {
      "question_say": true,
      "question_show": true,
      "answer_type": "text_data",
      "answer": 514,
      "question_type": "multiple-choice",
      "stimulus_type": "text_data",
      "responsetype_set": [
        "text_data",
        "text_data",
        "text_data"
      ],
      "stimulus": "513, __, 515, 516",
      "response_set": [
        514,
        236,
        570
      ],
      "gen_question": false
    },
    {
      "question_say": true,
      "question_show": true,
      "answer_type": "text_data",
      "answer": 649,
      "question_type": "multiple-choice",
      "stimulus_type": "text_data",
      "responsetype_set": [
        "text_data",
        "text_data",
        "text_data"
      ],
      "stimulus": "648, __, 650, 651",
      "response_set": [
        649,
        746,
        851
      ],
      "gen_question": false
    },
    {
      "question_say": true,
      "question_show": true,
      "answer_type": "text_data",
      "answer": 383,
      "question_type": "multiple-choice",
      "stimulus_type": "text_data",
      "responsetype_set": [
        "text_data",
        "text_data",
        "text_data"
      ],
      "stimulus": "382, __, 384, 385",
      "response_set": [
        720,
        715,
        383
      ],
      "gen_question": false
    },
    {
      "question_say": true,
      "question_show": true,
      "answer_type": "text_data",
      "answer": 347,
      "question_type": "multiple-choice",
      "stimulus_type": "text_data",
      "responsetype_set": [
        "text_data",
        "text_data",
        "text_data"
      ],
      "stimulus": "346, __, 348, 349",
      "response_set": [
        353,
        347,
        319
      ],
      "gen_question": false
    },
    {
      "question_say": true,
      "question_show": true,
      "answer_type": "text_data",
      "answer": 219,
      "question_type": "multiple-choice",
      "stimulus_type": "text_data",
      "responsetype_set": [
        "text_data",
        "text_data",
        "text_data"
      ],
      "stimulus": "218, __, 220, 221",
      "response_set": [
        577,
        219,
        868
      ],
      "gen_question": false
    },
    {
      "question_say": true,
      "question_show": true,
      "answer_type": "text_data",
      "answer": 886,
      "question_type": "multiple-choice",
      "stimulus_type": "text_data",
      "responsetype_set": [
        "text_data",
        "text_data",
        "text_data"
      ],
      "stimulus": "885, __, 887, 888",
      "response_set": [
        549,
        886,
        599
      ],
      "gen_question": false
    },
    {
      "question_say": true,
      "question_show": true,
      "answer_type": "text_data",
      "answer": 396,
      "question_type": "multiple-choice",
      "stimulus_type": "text_data",
      "responsetype_set": [
        "text_data",
        "text_data",
        "text_data"
      ],
      "stimulus": "395, __, 397, 398",
      "response_set": [
        396,
        310,
        247
      ],
      "gen_question": false
    },
    {
      "question_say": true,
      "question_show": true,
      "answer_type": "text_data",
      "answer": 294,
      "question_type": "multiple-choice",
      "stimulus_type": "text_data",
      "responsetype_set": [
        "text_data",
        "text_data",
        "text_data"
      ],
      "stimulus": "293, __, 295, 296",
      "response_set": [
        419,
        294,
        295
      ],
      "gen_question": false
    },
    {
      "question_say": true,
      "question_show": true,
      "answer_type": "text_data",
      "answer": 865,
      "question_type": "multiple-choice",
      "stimulus_type": "text_data",
      "responsetype_set": [
        "text_data",
        "text_data",
        "text_data"
      ],
      "stimulus": "864, __, 866, 867",
      "response_set": [
        376,
        865,
        485
      ],
      "gen_question": false
    },
    {
      "question_say": true,
      "question_show": true,
      "answer_type": "text_data",
      "answer": 794,
      "question_type": "multiple-choice",
      "stimulus_type": "text_data",
      "responsetype_set": [
        "text_data",
        "text_data",
        "text_data"
      ],
      "stimulus": "793, __, 795, 796",
      "response_set": [
        794,
        739,
        615
      ],
      "gen_question": false
    },
    {
      "question_say": true,
      "question_show": true,
      "answer_type": "text_data",
      "answer": 837,
      "question_type": "multiple-choice",
      "stimulus_type": "text_data",
      "responsetype_set": [
        "text_data",
        "text_data",
        "text_data"
      ],
      "stimulus": "836, __, 838, 839",
      "response_set": [
        794,
        837,
        695
      ],
      "gen_question": false
    },
    {
      "question_say": true,
      "question_show": true,
      "answer_type": "text_data",
      "answer": 366,
      "question_type": "multiple-choice",
      "stimulus_type": "text_data",
      "responsetype_set": [
        "text_data",
        "text_data",
        "text_data"
      ],
      "stimulus": "365, __, 367, 368",
      "response_set": [
        442,
        890,
        366
      ],
      "gen_question": false
    },
    {
      "question_say": true,
      "question_show": true,
      "answer_type": "text_data",
      "answer": 804,
      "question_type": "multiple-choice",
      "stimulus_type": "text_data",
      "responsetype_set": [
        "text_data",
        "text_data",
        "text_data"
      ],
      "stimulus": "803, __, 805, 806",
      "response_set": [
        468,
        804,
        715
      ],
      "gen_question": false
    },
    {
      "question_say": true,
      "question_show": true,
      "answer_type": "text_data",
      "answer": 118,
      "question_type": "multiple-choice",
      "stimulus_type": "text_data",
      "responsetype_set": [
        "text_data",
        "text_data",
        "text_data"
      ],
      "stimulus": "117, __, 119, 120",
      "response_set": [
        608,
        202,
        118
      ],
      "gen_question": false
    },
    {
      "question_say": true,
      "question_show": true,
      "answer_type": "text_data",
      "answer": 219,
      "question_type": "multiple-choice",
      "stimulus_type": "text_data",
      "responsetype_set": [
        "text_data",
        "text_data",
        "text_data"
      ],
      "stimulus": "218, __, 220, 221",
      "response_set": [
        829,
        219,
        141
      ],
      "gen_question": false
    },
    {
      "question_say": true,
      "question_show": true,
      "answer_type": "text_data",
      "answer": 736,
      "question_type": "multiple-choice",
      "stimulus_type": "text_data",
      "responsetype_set": [
        "text_data",
        "text_data",
        "text_data"
      ],
      "stimulus": "735, __, 737, 738",
      "response_set": [
        736,
        184,
        239
      ],
      "gen_question": false
    },
    {
      "question_say": true,
      "question_show": true,
      "answer_type": "text_data",
      "answer": 811,
      "question_type": "multiple-choice",
      "stimulus_type": "text_data",
      "responsetype_set": [
        "text_data",
        "text_data",
        "text_data"
      ],
      "stimulus": "810, __, 812, 813",
      "response_set": [
        719,
        811,
        239
      ],
      "gen_question": false
    },
    {
      "question_say": true,
      "question_show": true,
      "answer_type": "text_data",
      "answer": 559,
      "question_type": "multiple-choice",
      "stimulus_type": "text_data",
      "responsetype_set": [
        "text_data",
        "text_data",
        "text_data"
      ],
      "stimulus": "558, __, 560, 561",
      "response_set": [
        580,
        285,
        559
      ],
      "gen_question": false
    },
    {
      "question_say": true,
      "question_show": true,
      "answer_type": "text_data",
      "answer": 529,
      "question_type": "multiple-choice",
      "stimulus_type": "text_data",
      "responsetype_set": [
        "text_data",
        "text_data",
        "text_data"
      ],
      "stimulus": "528, __, 530, 531",
      "response_set": [
        529,
        586,
        569
      ],
      "gen_question": false
    },
    {
      "question_say": true,
      "question_show": true,
      "answer_type": "text_data",
      "answer": 332,
      "question_type": "multiple-choice",
      "stimulus_type": "text_data",
      "responsetype_set": [
        "text_data",
        "text_data",
        "text_data"
      ],
      "stimulus": "331, __, 333, 334",
      "response_set": [
        746,
        332,
        109
      ],
      "gen_question": false
    },
    {
      "question_say": true,
      "question_show": true,
      "answer_type": "text_data",
      "answer": 892,
      "question_type": "multiple-choice",
      "stimulus_type": "text_data",
      "responsetype_set": [
        "text_data",
        "text_data",
        "text_data"
      ],
      "stimulus": "891, __, 893, 894",
      "response_set": [
        628,
        458,
        892
      ],
      "gen_question": false
    },
    {
      "question_say": true,
      "question_show": true,
      "answer_type": "text_data",
      "answer": 225,
      "question_type": "multiple-choice",
      "stimulus_type": "text_data",
      "responsetype_set": [
        "text_data",
        "text_data",
        "text_data"
      ],
      "stimulus": "224, __, 226, 227",
      "response_set": [
        225,
        717,
        366
      ],
      "gen_question": false
    },
    {
      "question_say": true,
      "question_show": true,
      "answer_type": "text_data",
      "answer": 186,
      "question_type": "multiple-choice",
      "stimulus_type": "text_data",
      "responsetype_set": [
        "text_data",
        "text_data",
        "text_data"
      ],
      "stimulus": "185, __, 187, 188",
      "response_set": [
        186,
        587,
        773
      ],
      "gen_question": false
    }
  ],
  "view_background": {
    "layout": "grid",
    "kind": "squares",
    "layoutcount": 0,
    "style": "primitives",
    "colorchoice": "fixed",
    "colorbase": "#666666",
    "colors": [
      -6053120,
      -7566336,
      -2500352,
      -5066240
    ]
  }
}